[
  {
    "id": "c1",
    "name": "Slovan Liberec",
    "shortName": "Slovan",
    "tla": "SLO",
    "crest": "/images/badges/chl-463.png",
    "kitHome": "#000000",
    "kitAway": "#FFFFFF",
    "stadium": "Stadion u Nisy",
    "city": "Liberec",
    "founded": 1921,
    "stadiumCapacity": "9900",
    "budget": 33,
    "wageBudget": 71,
    "apiId": 463,
    "manager": {
      "name": "R. Kováč",
      "nationality": "CZE",
      "age": 46,
      "image": "/images/coaches/coach-37510953.png",
      "contractEnd": null,
      "apiId": 37510953
    }
  },
  {
    "id": "c2",
    "name": "Hradec Králové",
    "shortName": "Hradec",
    "tla": "HRA",
    "crest": "/images/badges/chl-3552.png",
    "kitHome": "#000000",
    "kitAway": "#FFFFFF",
    "stadium": "Malšovická Aréna",
    "city": "",
    "founded": 1905,
    "stadiumCapacity": "9300",
    "budget": 29,
    "wageBudget": 88,
    "apiId": 3552,
    "manager": {
      "name": "David Horejs",
      "nationality": "CZE",
      "age": 48,
      "image": "/images/coaches/coach-78594.png",
      "contractEnd": "2027-06-30",
      "apiId": 78594
    }
  },
  {
    "id": "c3",
    "name": "Dukla Praha",
    "shortName": "Dukla",
    "tla": "DUK",
    "crest": "/images/badges/chl-3531.png",
    "kitHome": "#000000",
    "kitAway": "#FFFFFF",
    "stadium": "Stadion Juliska",
    "city": "Praha",
    "founded": 1948,
    "stadiumCapacity": "8150",
    "budget": 17,
    "wageBudget": 119,
    "apiId": 3531,
    "manager": {
      "name": "Pavel Šustr",
      "nationality": "CZE",
      "age": 51,
      "image": "/images/coaches/coach-22513675.png",
      "contractEnd": null,
      "apiId": 22513675
    }
  },
  {
    "id": "c4",
    "name": "Sparta Praha",
    "shortName": "SPA",
    "tla": "SPA",
    "crest": "/images/badges/chl-2727.png",
    "kitHome": "#000000",
    "kitAway": "#FFFFFF",
    "stadium": "Epet Arena",
    "city": "Praha",
    "founded": 1893,
    "stadiumCapacity": "8000",
    "budget": 13,
    "wageBudget": 89,
    "apiId": 2727,
    "manager": {
      "name": "Lars Friis",
      "nationality": "DEN",
      "age": 49,
      "image": "/images/coaches/coach-37563968.png",
      "contractEnd": null,
      "apiId": 37563968
    }
  },
  {
    "id": "c5",
    "name": "Slovácko",
    "shortName": "SLO",
    "tla": "SLO",
    "crest": "/images/badges/chl-234.png",
    "kitHome": "#000000",
    "kitAway": "#FFFFFF",
    "stadium": "Městský fotbalový stadion Miroslava Valenty",
    "city": "Uherské Hradiště",
    "founded": 1927,
    "stadiumCapacity": "8000",
    "budget": 26,
    "wageBudget": 64,
    "apiId": 234,
    "manager": {
      "name": "Roman Skuhravý",
      "nationality": "CZE",
      "age": 51,
      "image": "/images/coaches/coach-1452449.png",
      "contractEnd": null,
      "apiId": 1452449
    }
  },
  {
    "id": "c6",
    "name": "Karviná",
    "shortName": "Karviná",
    "tla": "KAR",
    "crest": "/images/badges/chl-512.png",
    "kitHome": "#000000",
    "kitAway": "#FFFFFF",
    "stadium": "Městský Stadión",
    "city": "Karviná",
    "founded": 2003,
    "stadiumCapacity": "5000",
    "budget": 24,
    "wageBudget": 44,
    "apiId": 512,
    "manager": null
  },
  {
    "id": "c7",
    "name": "Baník Ostrava",
    "shortName": "Baník",
    "tla": "BAN",
    "crest": "/images/badges/chl-3269.png",
    "kitHome": "#000000",
    "kitAway": "#FFFFFF",
    "stadium": "Městský stadion - Vítkovice Aréna",
    "city": "Ostrava",
    "founded": 1922,
    "stadiumCapacity": "15123",
    "budget": 27,
    "wageBudget": 115,
    "apiId": 3269,
    "manager": {
      "name": "Ondrej Smetana",
      "nationality": "CZE",
      "age": 43,
      "image": "/images/coaches/coach-36969.png",
      "contractEnd": null,
      "apiId": 36969
    }
  },
  {
    "id": "c8",
    "name": "Sigma Olomouc",
    "shortName": "Sigma",
    "tla": "SIG",
    "crest": "/images/badges/chl-3097.png",
    "kitHome": "#000000",
    "kitAway": "#FFFFFF",
    "stadium": "Andrův stadion",
    "city": "Olomouc",
    "founded": 1919,
    "stadiumCapacity": "12566",
    "budget": 13,
    "wageBudget": 43,
    "apiId": 3097,
    "manager": {
      "name": "Tomas Janotka",
      "nationality": "CZE",
      "age": 44,
      "image": "/images/coaches/coach-79002.png",
      "contractEnd": null,
      "apiId": 79002
    }
  },
  {
    "id": "c9",
    "name": "Zlín",
    "shortName": "Zlín",
    "tla": "ZLÍ",
    "crest": "/images/badges/chl-1745.png",
    "kitHome": "#000000",
    "kitAway": "#FFFFFF",
    "stadium": "Stadion Letná",
    "city": "Zlín",
    "founded": 1919,
    "stadiumCapacity": "5898",
    "budget": 11,
    "wageBudget": 53,
    "apiId": 1745,
    "manager": {
      "name": "Bronislav Cervenka",
      "nationality": "CZE",
      "age": 50,
      "image": "/images/coaches/coach-82054.png",
      "contractEnd": null,
      "apiId": 82054
    }
  },
  {
    "id": "c10",
    "name": "Teplice",
    "shortName": "Teplice",
    "tla": "TEP",
    "crest": "/images/badges/chl-1351.png",
    "kitHome": "#000000",
    "kitAway": "#FFFFFF",
    "stadium": "Na Stínadlech",
    "city": "Teplice",
    "founded": 1945,
    "stadiumCapacity": "17078",
    "budget": 29,
    "wageBudget": 47,
    "apiId": 1351,
    "manager": {
      "name": "Zdenko Frťala",
      "nationality": "SVK",
      "age": 55,
      "image": "/images/coaches/coach-1512207.png",
      "contractEnd": null,
      "apiId": 1512207
    }
  },
  {
    "id": "c11",
    "name": "Slavia Praha",
    "shortName": "SLA",
    "tla": "SLA",
    "crest": "/images/badges/chl-216.png",
    "kitHome": "#000000",
    "kitAway": "#FFFFFF",
    "stadium": "Fortuna Arena",
    "city": "Praha",
    "founded": 1892,
    "stadiumCapacity": "19370",
    "budget": 31,
    "wageBudget": 57,
    "apiId": 216,
    "manager": {
      "name": "Jindřich Trpišovský",
      "nationality": "CZE",
      "age": 50,
      "image": "/images/coaches/coach-455705.png",
      "contractEnd": "2029-06-30",
      "apiId": 455705
    }
  },
  {
    "id": "c12",
    "name": "Pardubice",
    "shortName": "Pardubice",
    "tla": "PAR",
    "crest": "/images/badges/chl-4484.png",
    "kitHome": "#000000",
    "kitAway": "#FFFFFF",
    "stadium": "CFIG Aréna",
    "city": "",
    "founded": 2008,
    "stadiumCapacity": "4620",
    "budget": 29,
    "wageBudget": 113,
    "apiId": 4484,
    "manager": null
  },
  {
    "id": "c13",
    "name": "Mladá Boleslav",
    "shortName": "Mladá",
    "tla": "MLA",
    "crest": "/images/badges/chl-187.png",
    "kitHome": "#000000",
    "kitAway": "#FFFFFF",
    "stadium": "Lokotrans Aréna (Mladá Boleslav)",
    "city": "Mladá Boleslav",
    "founded": 1902,
    "stadiumCapacity": "5000",
    "budget": 17,
    "wageBudget": 117,
    "apiId": 187,
    "manager": {
      "name": "A. Majer",
      "nationality": "UNK",
      "age": 46,
      "image": "/images/coaches/coach-37761621.png",
      "contractEnd": null,
      "apiId": 37761621
    }
  },
  {
    "id": "c14",
    "name": "Jablonec",
    "shortName": "Jablonec",
    "tla": "JAB",
    "crest": "/images/badges/chl-3643.png",
    "kitHome": "#000000",
    "kitAway": "#FFFFFF",
    "stadium": "Stadion Střelnice",
    "city": "Jablonec nad Nisou",
    "founded": 1945,
    "stadiumCapacity": "6280",
    "budget": 34,
    "wageBudget": 72,
    "apiId": 3643,
    "manager": {
      "name": "Jiri Vagner",
      "nationality": "CZE",
      "age": 44,
      "image": "/images/coaches/coach-37631601.png",
      "contractEnd": null,
      "apiId": 37631601
    }
  },
  {
    "id": "c15",
    "name": "Viktoria Plzeň",
    "shortName": "VPL",
    "tla": "VPL",
    "crest": "/images/badges/chl-3545.png",
    "kitHome": "#000000",
    "kitAway": "#FFFFFF",
    "stadium": "Doosan Aréna",
    "city": "Plzeň",
    "founded": 1911,
    "stadiumCapacity": "11700",
    "budget": 27,
    "wageBudget": 83,
    "apiId": 3545,
    "manager": {
      "name": "Martin Hysky",
      "nationality": "CZE",
      "age": 50,
      "image": "/images/coaches/coach-35441.png",
      "contractEnd": "2028-06-30",
      "apiId": 35441
    }
  },
  {
    "id": "c16",
    "name": "Bohemians 1905",
    "shortName": "Bohemians",
    "tla": "BOH",
    "crest": "/images/badges/chl-2488.png",
    "kitHome": "#000000",
    "kitAway": "#FFFFFF",
    "stadium": "Stadion Dolícek",
    "city": "Praha",
    "founded": 1905,
    "stadiumCapacity": "6300",
    "budget": 32,
    "wageBudget": 95,
    "apiId": 2488,
    "manager": {
      "name": "Jaroslav Veselý",
      "nationality": "CZE",
      "age": 48,
      "image": "/images/coaches/coach-37259986.png",
      "contractEnd": "2028-06-30",
      "apiId": 37259986
    }
  }
]