[
  {
    "id": "c1",
    "name": "Domžale",
    "shortName": "Domžale",
    "tla": "DOM",
    "crest": "/images/badges/svn-820.png",
    "kitHome": "#000000",
    "kitAway": "#FFFFFF",
    "stadium": "Športni Park",
    "city": "Domžale",
    "founded": 1921,
    "stadiumCapacity": "2341",
    "budget": 13,
    "wageBudget": 48,
    "apiId": 820,
    "manager": {
      "name": "Anton Žlogar",
      "nationality": "SVN",
      "age": 25,
      "image": "/images/coaches/coach-465433.png",
      "contractEnd": null,
      "apiId": 465433
    }
  },
  {
    "id": "c2",
    "name": "Bravo",
    "shortName": "Bravo",
    "tla": "BRA",
    "crest": "/images/badges/svn-95999.png",
    "kitHome": "#000000",
    "kitAway": "#FFFFFF",
    "stadium": "Štadion ŽŠD",
    "city": "Ljubljana",
    "founded": 2006,
    "stadiumCapacity": "3000",
    "budget": 34,
    "wageBudget": 90,
    "apiId": 95999,
    "manager": {
      "name": "Aleš Arnol",
      "nationality": "SVN",
      "age": 25,
      "image": "/images/coaches/coach-37686605.png",
      "contractEnd": "2028-06-30",
      "apiId": 37686605
    }
  },
  {
    "id": "c3",
    "name": "Mura",
    "shortName": "Mura",
    "tla": "MUR",
    "crest": "/images/badges/svn-10695.png",
    "kitHome": "#000000",
    "kitAway": "#FFFFFF",
    "stadium": "Mesti Stadion Fazanerija",
    "city": "Murska Sobota",
    "founded": 2012,
    "stadiumCapacity": "5000",
    "budget": 20,
    "wageBudget": 69,
    "apiId": 10695,
    "manager": {
      "name": "Darjan Slavic",
      "nationality": "UNK",
      "age": 43,
      "image": "/images/coaches/coach-37711428.png",
      "contractEnd": null,
      "apiId": 37711428
    }
  },
  {
    "id": "c4",
    "name": "Olimpija",
    "shortName": "Olimpija",
    "tla": "OLI",
    "crest": "/images/badges/svn-1453.png",
    "kitHome": "#000000",
    "kitAway": "#FFFFFF",
    "stadium": "Stadion Stožice",
    "city": "Ljubljana",
    "founded": 1911,
    "stadiumCapacity": "16432",
    "budget": 21,
    "wageBudget": 52,
    "apiId": 1453,
    "manager": {
      "name": "Federico Bessone Luna",
      "nationality": "ARG",
      "age": 42,
      "image": "/images/coaches/coach-4890.png",
      "contractEnd": null,
      "apiId": 4890
    }
  },
  {
    "id": "c5",
    "name": "Radomlje",
    "shortName": "Radomlje",
    "tla": "RAD",
    "crest": "/images/badges/svn-7436.png",
    "kitHome": "#000000",
    "kitAway": "#FFFFFF",
    "stadium": "Športni park Radomlje",
    "city": "Radomlje",
    "founded": 0,
    "stadiumCapacity": "500",
    "budget": 10,
    "wageBudget": 77,
    "apiId": 7436,
    "manager": null
  },
  {
    "id": "c6",
    "name": "Aluminij",
    "shortName": "Aluminij",
    "tla": "ALU",
    "crest": "/images/badges/svn-3291.png",
    "kitHome": "#000000",
    "kitAway": "#FFFFFF",
    "stadium": "Športni Park Aluminij",
    "city": "Kidričevo",
    "founded": 1946,
    "stadiumCapacity": "2600",
    "budget": 17,
    "wageBudget": 58,
    "apiId": 3291,
    "manager": null
  },
  {
    "id": "c7",
    "name": "Maribor",
    "shortName": "Maribor",
    "tla": "MAR",
    "crest": "/images/badges/svn-2973.png",
    "kitHome": "#000000",
    "kitAway": "#FFFFFF",
    "stadium": "Ljudski vrt",
    "city": "Maribor",
    "founded": 1960,
    "stadiumCapacity": "12702",
    "budget": 18,
    "wageBudget": 95,
    "apiId": 2973,
    "manager": {
      "name": "Feda Dudic",
      "nationality": "BIH",
      "age": 43,
      "image": "/images/coaches/coach-65789.png",
      "contractEnd": "2027-06-30",
      "apiId": 65789
    }
  },
  {
    "id": "c8",
    "name": "Koper",
    "shortName": "Koper",
    "tla": "KOP",
    "crest": "/images/badges/svn-444.png",
    "kitHome": "#000000",
    "kitAway": "#FFFFFF",
    "stadium": "ŠRC Bonifika",
    "city": "Koper",
    "founded": 1920,
    "stadiumCapacity": "4010",
    "budget": 18,
    "wageBudget": 70,
    "apiId": 444,
    "manager": {
      "name": "Zoran Željkovič",
      "nationality": "SVN",
      "age": 45,
      "image": "/images/coaches/coach-75773.png",
      "contractEnd": null,
      "apiId": 75773
    }
  },
  {
    "id": "c9",
    "name": "Primorje",
    "shortName": "Primorje",
    "tla": "PRI",
    "crest": "/images/badges/svn-8139.png",
    "kitHome": "#000000",
    "kitAway": "#FFFFFF",
    "stadium": "Nogometni stadion Ajdovščina",
    "city": "Ajdovščina",
    "founded": 2011,
    "stadiumCapacity": "3000",
    "budget": 20,
    "wageBudget": 108,
    "apiId": 8139,
    "manager": {
      "name": "Anton Žlogar",
      "nationality": "SVN",
      "age": 25,
      "image": "/images/coaches/coach-465433.png",
      "contractEnd": null,
      "apiId": 465433
    }
  },
  {
    "id": "c10",
    "name": "Celje",
    "shortName": "Celje",
    "tla": "CEL",
    "crest": "/images/badges/svn-1114.png",
    "kitHome": "#000000",
    "kitAway": "#FFFFFF",
    "stadium": "Stadion Z'dežele",
    "city": "Celje",
    "founded": 1919,
    "stadiumCapacity": "16038",
    "budget": 28,
    "wageBudget": 58,
    "apiId": 1114,
    "manager": {
      "name": "Vítor de Carvalho Campelos",
      "nationality": "POR",
      "age": 50,
      "image": "/images/coaches/coach-1552838.png",
      "contractEnd": "2028-06-30",
      "apiId": 1552838
    }
  }
]